nonebot_plugin_mcversion-0.3.7.dist-info/METADATA
nonebot_plugin_mcversion-0.3.7.dist-info/WHEEL
nonebot_plugin_mcversion-0.3.7.dist-info/entry_points.txt
nonebot_plugin_mcversion-0.3.7.dist-info/licenses/LICENSE
nonebot_plugin_mcversion/__init__.py
nonebot_plugin_mcversion-0.3.7.dist-info/RECORD
