Metadata-Version: 2.1
Name: nonebot-plugin-mcversion
Version: 0.3.7
Summary: NoneBot2 plugin for CheckMCupdate
Author-Email: CN171-1 <CN171_11_@outlook.com>
License: MIT
Project-URL: Homepage, https://github.com/CN171-1/nonebot-plugin-mcversion
Project-URL: Repository, https://github.com/CN171-1/nonebot-plugin-mcversion
Requires-Python: >=3.9
Requires-Dist: nonebot2>=2.0.0rc2
Requires-Dist: nonebot-adapter-onebot>=2.1.5
Requires-Dist: nonebot-plugin-apscheduler>=0.2.0
Requires-Dist: httpx>=0.24.0
